emdemor_app_template/__init__.py
emdemor_app_template/__main__.py
emdemor_app_template/_version.py
emdemor_app_template/utils.py
emdemor_app_template/mymodule/__init__.py
emdemor_app_template/mymodule/hello.py
emdemor_app_template-0.0.3.dist-info/LICENSE
emdemor_app_template-0.0.3.dist-info/METADATA
emdemor_app_template-0.0.3.dist-info/WHEEL
emdemor_app_template-0.0.3.dist-info/entry_points.txt
emdemor_app_template-0.0.3.dist-info/top_level.txt
emdemor_app_template-0.0.3.dist-info/RECORD
