Metadata-Version: 2.1
Name: emdemor-app-template
Version: 0.0.3
Summary: Um template para começar o desenvolvimento de apps
Author-email: Eduardo <emdemor415@gmail.com.br>
License: Copyright (c) 2023, Eduardo Morais
Keywords: template,app
Classifier: Environment :: Console
Classifier: License :: OSI Approved :: MIT License
Classifier: Natural Language :: Portuguese (Brazilian)
Classifier: Operating System :: OS Independent
Classifier: Programming Language :: Python :: 3
Classifier: Programming Language :: Python :: 3.9
Classifier: Programming Language :: Python :: 3.10
Classifier: Topic :: Utilities
Requires-Python: >=3.9
License-File: LICENSE
